Metadata-Version: 2.1
Name: nonecorn
Version: 0.17.3
Summary: A ASGI Server forked from hypercorn with more extra feature beyond ASGI
Home-page: https://gitlab.com/pgjones/hypercorn/
Author: P G Jones
Author-email: philip.graham.jones@googlemail.com
License: MIT
Classifier: Development Status :: 4 - Beta
Classifier: Environment :: Web Environment
Classifier: Intended Audience :: Developers
Classifier: License :: OSI Approved :: MIT License
Classifier: Operating System :: OS Independent
Classifier: Programming Language :: Python
Classifier: Programming Language :: Python :: 3
Classifier: Programming Language :: Python :: 3.7
Classifier: Programming Language :: Python :: 3.8
Classifier: Programming Language :: Python :: 3.9
Classifier: Programming Language :: Python :: 3.10
Classifier: Programming Language :: Python :: 3.11
Classifier: Programming Language :: Python :: 3.12
Classifier: Topic :: Internet :: WWW/HTTP :: Dynamic Content
Classifier: Topic :: Software Development :: Libraries :: Python Modules
Requires-Python: >=3.7
License-File: LICENSE
Requires-Dist: h11
Requires-Dist: h2 >=3.1.0
Requires-Dist: priority
Requires-Dist: exceptiongroup >=1.1.0
Requires-Dist: wsproto >=0.14.0
Requires-Dist: tomli ; python_version < "3.11"
Requires-Dist: taskgroup ; python_version < "3.11"
Requires-Dist: typing-extensions >=3.7.4 ; python_version < "3.8"
Provides-Extra: h3
Requires-Dist: aioquic <1.0,>=0.9.0 ; extra == 'h3'
Provides-Extra: tests
Requires-Dist: hypothesis ; extra == 'tests'
Requires-Dist: mock ; extra == 'tests'
Requires-Dist: pytest ; extra == 'tests'
Requires-Dist: pytest-asyncio ; extra == 'tests'
Requires-Dist: pytest-cov ; extra == 'tests'
Requires-Dist: pytest-trio ; extra == 'tests'
Requires-Dist: trio ; extra == 'tests'
Provides-Extra: trio
Requires-Dist: trio >=0.11.0 ; extra == 'trio'
Provides-Extra: uvloop
Requires-Dist: uvloop ; extra == 'uvloop'
